disqusapi
