Metadata-Version: 1.0
Name: disqus-python
Version: 0.4.2
Summary: Disqus API Bindings
Home-page: http://github.com/disqus/disqus-python
Author: DISQUS
Author-email: david@disqus.com
License: UNKNOWN
Platform: UNKNOWN
Classifier: Intended Audience :: Developers
Classifier: Intended Audience :: System Administrators
Classifier: Operating System :: OS Independent
Classifier: Topic :: Software Development
